Workbook

Sheet 方案
A1: 方案提报任务（截止到8月17日）
A2: 序号 | B2: 任务标题 | C2: 任务类型 | D2: 创建时间 | E2: 计划开始时间 | F2: 计划结束时间 | G2: 实际完成时间 | H2: 计划工时 | I2: 实际工时 | J2: 创建人 | K2: 当前进展 | L2: 项目状态 （进行中 / 已结项-签约 / 已结项-丢单 / 暂停） | M2: 丢单原因 （客户失联 / 选其他供应商 / 预算不足 / 需求不实 / 价格 / 交期 / 其他）
A3: 1 | B3: C00003352｜陈辉｜工业｜埃及4万吨料场项目｜方案V1（预算） | C3: 方案 | D3: 2026-07-21 14:19:20 | E3: 2026-07-21 14:11:00 | F3: 2026-07-24 19:00:00 | G3: 2026-07-24 17:10:52 | H3: 3.2天 | I3: 3.2天 | J3: 陈辉 | K3: =VLOOKUP(B3,[2]方案!$B:$K,10,FALSE) -> TCI预期拿到了埃及一港口的运营权，有计划建散料库，已报预算，还在规划阶段。 | L3: 进行中
A4: 2 | B4: C00007339｜陈辉｜工业｜韩国大宇3万吨磷矿粉项目｜方案V1 | 重点项目 | C4: 方案 | D4: 2026-07-14 17:43:28 | E4: 2026-07-15 08:00:00 | F4: 2026-07-17 17:00:00 | G4: 2026-07-17 17:07:49 | H4: 2.4天 | I4: 2.4天 | J4: 陈辉 | K4: =VLOOKUP(B4,[2]方案!$B:$K,10,FALSE) -> 大宇在土库曼化肥厂项目，仓型各种变化和多次报价后，目前最后一版是焊接仓的EPC。用户和大宇还在比较仓型。 | L4: 进行中
A5: 3 | B5: C00001305｜陈辉｜工业｜韩国Jeju-四套污泥仓｜方案V1 | C5: 方案 | D5: 2026-07-02 17:47:15 | E5: 2026-07-03 08:00:00 | F5: 2026-07-09 17:00:00 | G5: 2026-07-09 15:04:26 | H5: 6.4天 | I5: 6.3天 | J5: 陈辉 | K5: =VLOOKUP(B5,[2]方案!$B:$K,10,FALSE) -> kim小项目，设计完仓型，客户改计划不需要了。 | L5: 已结项-丢单 | M5: 客户调整计划
A6: 4 | B6: C00001305｜陈辉｜工业｜韩国welcron5套污泥仓｜方案V1 | C6: 方案 | D6: 2026-07-02 17:03:09 | E6: 2026-07-02 16:58:00 | F6: 2026-07-06 19:00:00 | G6: 2026-07-03 18:25:38 | H6: 4.1天 | I6: 1.1天 | J6: 陈辉 | K6: =VLOOKUP(B6,[2]方案!$B:$K,10,FALSE) -> kim小项目，设计完仓型，客户改计划不需要了。 | L6: 已结项-丢单 | M6: 客户调整计划
A7: 5 | B7: C00001305｜陈辉｜工业｜韩国140立方米 x 3套树脂仓｜方案V1 | C7: 方案 | D7: 2026-06-29 17:36:48 | E7: 2026-06-30 08:00:00 | F7: 2026-07-03 19:00:00 | G7: 2026-07-03 18:25:43 | H7: 3.5天 | I7: 3.5天 | J7: 陈辉 | K7: =VLOOKUP(B7,[2]方案!$B:$K,10,FALSE) -> 小项目，仅仓无设备，客户还在决策。 | L7: 暂停
A8: 6 | B8: C00002715｜陈辉｜工业｜塞拉利昂2个3万吨clinker项目｜方案V1 | 重点项目 | C8: 方案 | D8: 2026-06-22 11:34:22 | E8: 2026-06-22 11:28:00 | F8: 2026-06-26 19:00:00 | G8: 2026-06-26 17:46:47 | H8: 4.3天 | I8: 4.3天 | J8: 陈辉 | K8: =VLOOKUP(B8,[2]方案!$B:$K,10,FALSE) -> 已去拜访客户，客户想法很多，缺资金。 | L8: 进行中
A9: 7 | B9: C00009463｜陈辉｜粮食｜突尼斯粮仓6x5,000t+10x8,000t｜方案V1 | C9: 方案 | D9: 2026-06-22 11:26:51 | E9: 2026-06-22 11:06:00 | F9: 2026-07-06 19:00:00 | G9: 2026-07-06 20:16:53 | H9: 14.3天 | I9: 14.4天 | J9: 陈辉 | K9: =VLOOKUP(B9,[2]方案!$B:$K,10,FALSE) -> 突尼斯一家工程公司想建这几个粮仓，没有资金，要靠国外银行给贷款，介绍了TCI给他们。项目还在找钱的阶段。 | L9: 进行中
A10: 8 | B10: C00001305｜陈辉｜工业｜韩国3,000立方米 x 2套石膏粉仓｜方案V2 | C10: 方案 | D10: 2026-05-27 11:38:18 | E10: 2026-05-27 11:27:00 | F10: 2026-07-02 19:29:00 | G10: 2026-07-02 18:33:52 | H10: 36.4天 | I10: 36.3天 | J10: 陈辉 | K10: =VLOOKUP(B10,[2]方案!$B:$K,10,FALSE) -> EPC，我方首次报价50Wusd，优化后及打折后价格42Wusd，业主说当地供应商报价32Wusd，且不需额外任何进口税费和运输费 | L10: 已结项-丢单 | M10: 选其他供应商 / 价格
A11: 9 | B11: C00009287｜陈辉｜工业｜大宇8套磷矿粉平底仓卸料｜方案V1 | C11: 方案 | D11: 2026-05-20 10:11:13 | E11: 2026-05-20 10:06:00 | F11: 2026-05-22 19:00:00 | G11: 2026-05-21 18:21:34 | H11: 2.4天 | I11: 1.4天 | J11: 陈辉 | K11: =VLOOKUP(B11,[2]方案!$B:$K,10,FALSE) -> 大宇在土库曼化肥厂项目，筒仓的卸料分包给了韩国的一家公司DY，我们给DY报价，仅报一次，技术澄清比较多，DY如果中标大概率优选选我们。 | L11: 进行中
A12: 10 | B12: C00009244｜陈辉｜工业｜火车卸料项目｜方案V1 | C12: 方案 | D12: 2026-05-18 15:56:16 | E12: 2026-05-18 15:51:00 | F12: 2026-05-22 19:00:00 | G12: 2026-05-22 18:13:36 | H12: 4.2天 | I12: 4.1天 | J12: 陈辉 | K12: =VLOOKUP(B12,[2]方案!$B:$K,10,FALSE) -> 客户自有仓，让我们报火车卸料后进仓和出仓相关设备。 客户的项目仍在计划评审阶段。 | L12: 进行中
A13: 11 | B13: C00008995｜陈辉｜粮食｜韩国港口粮食输送项目｜方案V1 | C13: 方案 | D13: 2026-03-12 10:21:50 | E13: 2026-03-12 10:11:00 | F13: 2026-03-18 17:00:00 | G13: 2026-03-19 09:09:05 | H13: 6.3天 | I13: 6.10天 | J13: 陈辉 | K13: =VLOOKUP(B13,[2]方案!$B:$K,10,FALSE) -> Kim联系的一个项目，已暂停。 | L13: 暂停
A14: 12 | B14: C00008180｜陈辉｜工业｜Lanwa水泥混拌系统｜方案V1 | 重点项目 | C14: 方案 | D14: =VLOOKUP(B14,[1]Sheet1!$A:$D,4,FALSE) -> 2026-08-17 09:00:35 | J14: 陈辉 | K14: =VLOOKUP(B14,[2]方案!$B:$K,10,FALSE) -> 老客户，项目含3个仓+混拌（mixer客户从其他供应商订购），客户中国通，对中国钢材加工价格十万分的了解，仅允许报价有合理利润，超出会选其他供应商。 | L14: 进行中
A15: 13 | B15: C00006497｜陈辉｜粮食｜埃及面粉项目｜方案V1（仅仓和钢构） | C15: 方案 | D15: =VLOOKUP(B15,[1]Sheet1!$A:$D,4,FALSE) -> 2026-08-10 12:18:07 | J15: 陈辉 | K15: =VLOOKUP(B15,[2]方案!$B:$K,10,FALSE) -> 埃及总包的一个投标项目，我们报价配合其投标。 | L15: 进行中
A16: 14 | B16: C00009849｜陈辉｜工业｜埃及3万吨混凝土仓（存氧化铝）项目｜方案V1 | C16: 方案 | D16: =VLOOKUP(B16,[1]Sheet1!$A:$D,4,FALSE) -> 2026-08-06 16:32:58 | J16: 陈辉 | K16: =VLOOKUP(B16,[2]方案!$B:$K,10,FALSE) -> 埃及的建筑公司作为投标人之一，向铝厂投标。 | L16: 进行中
A17: 15 | B17: C00009244｜陈辉｜工业｜巴西钢板仓和卸到火车项目｜方案V1 | C17: 方案 | D17: =VLOOKUP(B17,[1]Sheet1!$A:$D,4,FALSE) -> 2026-08-06 15:14:14 | J17: 陈辉 | K17: =VLOOKUP(B17,[2]方案!$B:$K,10,FALSE) -> 规划阶段，客户未来可能有两万吨粘土仓的需求，目前只是了解仓型和价格。 | L17: 进行中
A18: 16 | B18: C00009852｜陈辉｜工业｜澳洲8x6000t水泥装配仓｜方案V1（钢构量） | C18: 方案 | D18: =VLOOKUP(B18,[1]Sheet1!$A:$D,4,FALSE) -> 2026-07-31 15:23:27 | J18: 陈辉 | K18: =VLOOKUP(B18,[2]方案!$B:$K,10,FALSE) -> 预算。客户仍在评估是建造混凝土仓or钢板仓。 | L18: 进行中
A19: 17 | B19: C00003392｜陈辉｜工业｜莱歇6个热镀锌仓项目｜方案V1（钢构量） | C19: 方案 | D19: =VLOOKUP(B19,[1]Sheet1!$A:$D,4,FALSE) -> 2026-07-30 17:02:11 | J19: 陈辉 | K19: =VLOOKUP(B19,[2]方案!$B:$K,10,FALSE) -> 莱歇在台北正在做的磨粉项目，这几个仓是原本是业主范围，现在想拿出来询价，来决定是分包给莱歇去做还是业主自己做。 莱歇要求足够低价。 | L19: 进行中
A20: 18 | B20: C00009556｜陈子凡｜工业｜蒙古TESO 4x2500水泥中转站｜方案V1 | C20: 方案 | D20: 2026-07-21 23:34:13 | E20: 2026-07-22 08:00:00 | F20: 2026-07-23 18:00:00 | G20: 2026-07-23 20:20:58 | H20: 1.4天 | I20: 1.6天 | J20: 陈子凡 | K20: 给客户发了方案，待更新报价。准备报价中，但客户主业是食品，本次询价可能只是为了解投资预算。 8月份在蒙古期间约客户见面，客户见面意愿不强 | L20: 进行中
A21: 19 | B21: C00009734｜陈子凡｜粮食｜ 阿根廷6个面粉仓+3个润麦仓+1个麸皮仓 单仓｜重量计算+清单 | C21: 方案 | D21: 2026-07-09 10:54:39 | E21: 2026-07-09 10:53:00 | F21: 2026-07-14 18:00:00 | G21: 2026-07-14 19:52:34 | H21: 5.3天 | I21: 5.4天 | J21: 陈子凡 | K21: 报过价了，希望不大。客户为工程公司，项目投标中，且对方对中国供应链很了解，价格非常敏感 | L21: 进行中
A22: 20 | B22: C00007248｜陈子凡｜工业｜厄瓜多尔塑料方仓项目｜清单 | C22: 方案 | D22: 2026-07-01 10:15:31 | E22: 2026-07-01 09:12:00 | F22: 2026-07-02 18:12:00 | G22: 2026-07-02 11:38:03 | H22: 1.4天 | I22: 1.2天 | J22: 陈子凡 | K22: 客户比价中。提交报价后等通知，本次报价相比1期项目有上涨，客户大概率会找新供应商比价 | L22: 进行中
A23: 21 | B23: XXXXX｜陈子凡｜粮食｜北京生物质颗粒装车仓｜方案V1 | 初步方案 | C23: 方案 | D23: 2026-06-29 15:10:49 | E23: 2026-06-29 15:08:00 | F23: 2026-07-01 18:00:00 | G23: 2026-07-01 15:23:00 | H23: 2.1天 | I23: 2.1天 | J23: 陈子凡 | K23: 跟进中。项目较前期，联系人在出差，需要过一段时间再联系 | L23: 进行中
A24: 22 | B24: C00007247｜陈子凡｜工业｜MAK砖厂现有气力输送系统更新项目 ｜方案V1 | 重点项目 | C24: 方案 | D24: 2026-05-25 09:48:58 | E24: 2026-05-25 09:46:00 | F24: 2026-05-27 17:00:00 | G24: 2026-05-27 12:17:32 | H24: 2.3天 | I24: 2.2天 | J24: 陈子凡 | K24: 报价中 | L24: 进行中，近期可成交
A25: 23 | B25: C00009223｜陈子凡｜粮食｜马来西亚益海大豆仓单仓｜图纸+算重量V1 | C25: 方案 | D25: 2026-05-18 16:19:49 | E25: 2026-05-18 16:18:00 | F25: 2026-05-19 12:59:00 | G25: 2026-05-19 13:05:11 | H25: 0.9天 | I25: 0.9天 | J25: 陈子凡 | K25: 项目取消。中间人告知工厂砍掉了此项预算，改为修复现有筒仓 | L25: 已结项-丢单 | M25: 预算不足
A26: 24 | B26: C00009104｜陈子凡｜工业｜MONCEMENT 3x2000水泥中转站｜方案V2 | 重点项目 | C26: 方案 | D26: 2026-05-11 15:26:14 | E26: 2026-06-16 11:10:00 | F26: 2026-06-16 20:07:00 | G26: 2026-06-16 18:32:38 | H26: 0.4天 | I26: 0.4天 | J26: 陈子凡 | K26: 更新方案中。拜访后按要求更新方案，有望近期落地 | L26: 进行中
A27: 25 | B27: Manila 01｜陈子凡｜工业｜菲律宾生力集团机场临建项目｜算量V1 | C27: 方案 | D27: 2026-04-30 12:25:51 | E27: 2026-04-30 12:19:00 | F27: 2026-05-07 19:00:00 | G27: 2026-05-18 18:22:46 | H27: 7.3天 | I27: 18.3天 | J27: 陈子凡 | K27: 未参与 | L27: 已结项-丢单 | M27: 项目要求EPC，本项目土建占比很高，最终未参与
A28: 26 | B28: Manila 01｜陈子凡｜粮食｜SMC SHIPPING 平方仓项目｜方案V1 | C28: 方案 | D28: 2026-04-27 11:55:47 | E28: 2026-05-06 11:33:00 | F28: 2026-05-06 17:39:00 | G28: 2026-05-06 15:19:00 | H28: 0.3天 | I28: 0.2天 | J28: 陈子凡 | K28: 价格高，客户买了别人的，可能是越南的，我们在钢结构厂房上没有竞争力 | L28: 已结项-丢单 | M28: 价格高
A29: 27 | B29: C00009101｜陈子凡｜工业｜毛里求斯塑料颗粒圆仓（铝仓，单仓）｜方案+清单V1 | C29: 方案 | D29: 2026-04-08 10:29:20 | E29: 2026-04-08 10:28:00 | F29: 2026-04-14 18:00:00 | G29: 2026-04-14 16:17:41 | H29: 6.3天 | I29: 6.3天 | J29: 陈子凡 | K29: 项目较小，放弃 | L29: 已结项-丢单 | M29: 项目体量很小，客户要求多，纠结我们是不是工厂，故放弃
A30: 28 | B30: C00008912 ｜陈子凡｜工业｜印度尼西亚碳酸钙仓｜方案+清单V1 | C30: 方案 | D30: 2026-03-17 11:14:18 | E30: 2026-04-09 18:11:00 | F30: 2026-04-14 20:59:00 | G30: 2026-04-16 14:19:14 | H30: 5.1天 | I30: 6.9天 | J30: 陈子凡 | K30: 项目小，放弃 | L30: 已结项-丢单 | M30: 客户体量非常小，纠结价格，后续放弃
A31: 29 | B31: 20260304 菲律宾生力集团 取料机报价 | C31: 方案 | D31: 2026-03-04 09:32:36 | E31: 2026-03-04 09:31:00 | F31: 2026-03-06 17:00:00 | G31: 2026-03-04 15:46:35 | H31: 2.3天 | I31: 0.3天 | J31: 陈子凡 | K31: 等授标通知 | L31: 进行中
A32: 30 | B32: 20260302 C00007247 MAK 陈子凡 2x150吨小仓方案 报价 | C32: 方案 | D32: 2026-03-02 14:26:18 | E32: 2026-03-02 14:24:00 | F32: 2026-03-04 12:00:00 | G32: 2026-03-04 11:57:28 | H32: 1.9天 | I32: 1.9天 | J32: 陈子凡 | K32: 已成交 | L32: 结项-签约
A33: 31 | B33: 20260206 陈子凡 南美3x1000/3X2000/3X2500吨水泥仓方案+清单 | C33: 方案 | D33: 2026-02-06 08:48:33 | E33: 2026-02-06 08:46:00 | F33: 2026-02-06 18:00:00 | G33: 2026-02-06 16:13:22 | H33: 0.4天 | I33: 0.4天 | J33: 陈子凡 | K33: 项目真实性存疑 | L33: 已结项-丢单 | M33: 北京中间商询价项目，真实性存疑，后续不再合作
A34: 32 | B34: 20260113陈子凡 巴基斯坦4000吨稻壳颗粒仓及上料系统 | C34: 方案 | D34: 2026-01-13 17:45:20 | E34: 2026-01-14 08:00:00 | F34: 2026-02-05 12:02:00 | G34: 2026-02-05 10:02:32 | H34: 22.2天 | I34: 22.1天 | J34: 陈子凡 | K34: 项目暂停 | L34: 暂停
A35: 33 | B35: Manila01｜陈子凡｜粮食｜菲律宾4x2000吨锥底仓｜清单V1 | 报价清单 | C35: 方案 | D35: =VLOOKUP(B35,[1]Sheet1!$A:$D,4,FALSE) -> 2026-08-13 17:28:50 | J35: =VLOOKUP(B35,[1]Sheet1!$A:$J,10,FALSE) -> 陈子凡 | K35: 已提交报价，等反馈。单仓项目，上周报价，等反馈。 | L35: 进行中
A36: 34 | B36: C00005424|崔阳|工业|Sibur塑料颗粒的气力输送项目|方案V1 | C36: 方案 | D36: 2026-07-22 16:16:47 | E36: 2026-07-22 16:18:00 | F36: 2026-07-26 16:00:00 | H36: 4天 | J36: 崔阳
A37: 35 | B37: C00006570|崔阳|工业|Powerz螺旋输送机采购|方案V1 | C37: 方案 | D37: 2026-07-21 10:32:54 | E37: 2026-07-23 08:00:00 | F37: 2026-07-24 17:00:00 | G37: 2026-07-23 17:05:11 | H37: 1.4天 | I37: 0.4天 | J37: 崔阳
A38: 36 | B38: C00006458 崔阳|工业|达涅利 辊道和步进梁项目 |方案V1 | C38: 方案 | D38: 2026-07-09 12:29:38 | E38: 2026-07-14 08:00:00 | F38: 2026-07-26 17:00:00 | H38: 12.4天 | J38: 崔阳
A39: 37 | B39: C00009596 崔阳|工业|乌克兰AIK-EKO 铜矿石筒仓项目 |方案V1 | C39: 方案 | D39: 2026-07-08 11:23:44 | E39: 2026-07-09 08:00:00 | F39: 2026-07-13 18:00:00 | G39: 2026-07-13 18:19:36 | H39: 4.4天 | I39: 4.5天 | J39: 崔阳
A40: 38 | B40: C00009055 崔阳|工业|CC7 Europe 化工回收项目 |方案V1 | C40: 方案 | D40: 2026-07-07 17:35:29 | E40: 2026-07-08 08:00:00 | F40: 2026-07-12 18:00:00 | G40: 2026-07-14 14:58:24 | H40: 4.4天 | I40: 6.3天 | J40: 崔阳
A41: 39 | B41: C00006514|崔阳|工业|cotes哈萨克斯坦4个矿石仓项目|方案V1 | C41: 方案 | D41: 2026-07-07 14:44:06 | E41: 2026-07-07 08:00:00 | F41: 2026-07-09 18:00:00 | G41: 2026-07-09 17:27:22 | H41: 2.4天 | I41: 2.4天 | J41: 崔阳
A42: 40 | B42: C00009720|崔阳|工业|乌兹别克斯坦撒马尔罕3000吨水泥厂项目|方案V1 | C42: 方案 | D42: 2026-07-07 14:40:42 | E42: 2026-07-07 08:00:00 | F42: 2026-07-10 18:00:00 | G42: 2026-07-10 14:30:55 | H42: 3.4天 | I42: 3.3天 | J42: 崔阳
A43: 41 | B43: C00007843|崔阳|工业|Эннова散装机|方案V1 | C43: 方案 | D43: 2026-06-26 10:08:03 | E43: 2026-06-26 10:06:00 | F43: 2026-06-30 21:00:00 | G43: 2026-06-30 18:30:41 | H43: 4.5天 | I43: 4.4天 | J43: 崔阳
A44: 42 | B44: C00009506 |崔阳|粮食| RUSAGRO农作物种子加工厂项目|方案V1 | C44: 方案 | D44: 2026-06-18 15:47:16 | E44: 2026-06-18 15:31:00 | F44: 2026-07-24 17:00:00 | H44: 22.1天 | J44: 崔阳
A45: 43 | B45: C00009372 |崔阳|工业|UZMETKOMBINATA, FILIAL 铁合金及辅料石灰日间仓储整套工艺设备EPC项目 |方案V1 | C45: 方案 | D45: 2026-06-11 14:42:48 | E45: 2026-06-11 14:31:00 | F45: 2026-07-27 17:00:00 | G45: 2026-07-27 15:25:30 | H45: 43.1天 | I45: 46.1天 | J45: 崔阳
A46: 44 | B46: C00009055 崔阳|工业|CC7 Europe 石灰给料包项目 |方案V1 | C46: 方案 | D46: 2026-06-10 17:25:54 | E46: 2026-06-11 08:00:00 | F46: 2026-06-18 17:00:00 | G46: 2026-06-18 15:55:30 | H46: 7.4天 | I46: 7.4天 | J46: 崔阳
A47: 45 | B47: C00009398 |崔阳|工业|ООО «Бункер-Порт»氧化铝港口储存及输送项目|方案V1 | C47: 方案 | D47: 2026-06-10 15:46:17 | E47: 2026-06-10 15:43:00 | F47: 2026-06-29 17:00:00 | G47: 2026-06-26 14:05:32 | H47: 19.1天 | I47: 15.10天 | J47: 崔阳
A48: 46 | B48: C00006514|崔阳|工业|cotes烧碱和硫酸钠化工仓|方案V1 | C48: 方案 | D48: 2026-06-09 11:10:49 | E48: 2026-06-09 11:07:00 | F48: 2026-06-12 17:00:00 | G48: 2026-06-12 16:49:20 | H48: 3.3天 | I48: 3.3天 | J48: 崔阳
A49: 47 | B49: C00009347 |崔阳|粮食| Ebad Pir Moradian Global Skills 40000吨储粮项目|方案V1 | C49: 方案 | D49: 2026-06-05 14:25:18 | E49: 2026-06-16 14:21:00 | F49: 2026-07-24 17:00:00 | H49: 38.1天 | J49: 崔阳
A50: 48 | B50: C00001534|崔阳|粮食| 30000吨 SILOS KZ 粮储综合体项目|方案V1 | C50: 方案 | D50: 2026-06-04 11:56:36 | E50: 2026-06-04 11:54:00 | F50: 2026-06-11 17:00:00 | G50: 2026-06-11 18:03:30 | H50: 7.3天 | I50: 7.3天 | J50: 崔阳
A51: 49 | B51: C00001534|崔阳|粮食| 1000吨小麦仓SILOS KZ 粮仓项目|方案V1 | C51: 方案 | D51: 2026-06-03 17:19:40 | E51: 2026-06-04 08:00:00 | F51: 2026-06-06 17:00:00 | G51: 2026-06-06 16:58:15 | H51: 2.4天 | I51: 2.4天 | J51: 崔阳
A52: 50 | B52: C00009304|崔阳|粮食|ELFORS, OOO谷物码头项目|方案V1 | C52: 方案 | D52: 2026-05-26 09:19:00 | E52: 2026-05-26 09:17:00 | F52: 2026-06-26 17:00:00 | G52: 2026-06-26 14:25:10 | H52: 31.3天 | I52: 31.3天 | J52: 崔阳
A53: 51 | B53: C00007843|崔阳|工业|Эннова新库兹涅兹克电厂烟气净化与脱硫系统项目|方案V1 | C53: 方案 | D53: 2026-05-15 14:49:14 | E53: 2026-05-19 17:32:00 | F53: 2026-07-10 23:00:00 | H53: 52.3天 | J53: 崔阳
A54: 52 | B54: C00006570|崔阳|工业|POWERZ0508设备采购|方案V1 | C54: 方案 | D54: 2026-05-08 10:40:15 | E54: 2026-05-08 10:38:00 | F54: 2026-05-12 19:00:00 | G54: 2026-05-14 08:44:35 | H54: 4.4天 | I54: 5.10天 | J54: 崔阳
A55: 53 | B55: C00006514|崔阳|工业|cotes电厂粉煤灰|方案V2 | C55: 方案 | D55: 2026-05-07 18:38:29 | E55: 2026-05-08 08:00:00 | F55: 2026-06-25 19:00:00 | G55: 2026-06-25 10:30:42 | H55: 48.5天 | I55: 48.2天 | J55: 崔阳
A56: 54 | B56: C00009215|崔阳|粮食|Anush Grigoryan饲料储存仓项目|方案V1 | C56: 方案 | D56: 2026-05-07 18:24:54 | E56: 2026-05-08 08:00:00 | F56: 2026-05-12 19:00:00 | G56: 2026-05-12 17:02:43 | H56: 4.5天 | I56: 4.4天 | J56: 崔阳
A57: 55 | B57: C00007843|崔阳|工业|石灰料仓及气力输送设备|方案V1 | C57: 方案 | D57: 2026-04-23 16:41:37 | E57: 2026-04-23 16:38:00 | F57: 2026-04-30 19:00:00 | G57: 2026-04-30 16:04:15 | H57: 7.1天 | I57: 6.10天 | J57: 崔阳
A58: 56 | B58: C00007464|崔阳|工业|麻类作物深加工|方案V1 | C58: 方案 | D58: 2026-04-20 10:17:42 | E58: 2026-04-20 10:16:00 | F58: 2026-06-23 21:00:00 | G58: 2026-06-23 18:03:06 | H58: 64.5天 | I58: 64.4天 | J58: 崔阳
A59: 57 | B59: C00009095|崔阳|粮食|粮食储运系统|方案V1 | C59: 方案 | D59: 2026-04-07 16:09:43 | E59: 2026-04-07 16:08:00 | F59: 2026-04-17 19:00:00 | G59: 2026-04-17 18:56:16 | H59: 10.1天 | I59: 10.2天 | J59: 崔阳
A60: 58 | B60: C00009094|崔阳|粮食|75万吨小麦深加工项目|方案V1|重点项目 | C60: 方案 | D60: 2026-04-03 09:46:30 | E60: 2026-04-03 09:46:00 | F60: 2026-05-19 22:00:00 | G60: 2026-05-19 17:24:13 | H60: 46.5天 | I60: 46.4天 | J60: 崔阳
A61: 59 | B61: C00009064|崔阳|工业|75吨熟石灰钢板仓|方案V1 | C61: 方案 | D61: 2026-03-27 17:03:06 | E61: 2026-03-28 08:00:00 | F61: 2026-04-01 19:00:00 | G61: 2026-04-01 18:17:44 | H61: 4.5天 | I61: 4.5天 | J61: 崔阳
A62: 60 | B62: C00009061|崔阳|工业|500吨水泥钢板仓|方案V1 | C62: 方案 | D62: 2026-03-25 17:24:31 | E62: 2026-03-26 08:00:00 | F62: 2026-03-31 17:00:00 | G62: 2026-03-31 09:49:08 | H62: 5.4天 | I62: 5.1天 | J62: 崔阳
A63: 61 | B63: C00006570|崔阳|工业|灰渣气力输送项目|方案V1 | C63: 方案 | D63: 2026-03-24 10:30:17 | E63: 2026-03-24 10:28:00 | F63: 2026-03-28 17:00:00 | G63: 2026-03-28 08:58:22 | H63: 4.3天 | I63: 3.10天 | J63: 崔阳
A64: 62 | B64: C00006570 Powerz 崔阳 工业 底渣输送机 方案V1 | C64: 方案 | D64: 2026-03-14 09:21:21 | E64: 2026-03-14 09:19:00 | F64: 2026-03-18 10:00:00 | H64: 4天 | J64: 崔阳
A65: 63 | B65: C00005698 ООО УК "Астон" 崔阳 粮食 1350吨葵花籽仓 方案V1 | C65: 方案 | D65: 2026-03-12 11:39:15 | E65: 2026-03-12 10:40:00 | F65: 2026-03-14 19:00:00 | G65: 2026-03-14 15:17:00 | H65: 2.4天 | I65: 2.2天 | J65: 崔阳
A66: 64 | B66: C00006570 Powerz 崔阳 工业 旋转给料系统 方案V1 | C66: 方案 | D66: 2026-03-06 09:32:25 | E66: 2026-03-06 09:29:00 | F66: 2026-03-10 17:00:00 | G66: 2026-03-10 08:47:00 | H66: 4.3天 | I66: 3.10天 | J66: 崔阳
A67: 65 | B67: C00007843 | 崔阳 | 工业 | 哈萨克热列兹肯特热电站10号机组烟气净化（脱硫，除尘）项目 | 方案V1 | C67: 方案 | D67: 2026-03-05 10:12:27 | E67: 2026-03-05 10:05:00 | F67: 2026-03-11 17:00:00 | H67: 6.3天 | J67: 崔阳
A68: 66 | B68: C00006570 Powerz 崔阳 20260214 旋转阀 | C68: 方案 | D68: 2026-02-14 09:25:27 | E68: 2026-02-14 09:24:00 | F68: 2026-03-02 10:00:00 | G68: 2026-02-28 08:32:08 | H68: 16天 | I68: 13.10天 | J68: 崔阳
A69: 67 | B69: C00006514 KOTEC 崔阳 工业 装配仓 方案V2 | C69: 方案 | D69: 2026-02-04 11:01:52 | E69: 2026-02-04 11:00:00 | F69: 2026-03-14 19:00:00 | G69: 2026-03-12 14:32:35 | H69: 38.3天 | I69: 36.2天 | J69: 崔阳
A70: 68 | B70: C00008851 ROSATOM, GK 崔阳 工业 俄罗斯氧化铝仓 方案V1 | C70: 方案 | D70: 2026-01-28 10:46:59 | E70: 2026-01-28 10:42:00 | F70: 2026-03-04 19:00:00 | G70: 2026-03-04 18:28:34 | H70: 35.4天 | I70: 35.4天 | J70: 崔阳
A71: 69 | B71: C00007843 | 崔阳 | 工业 | 外贝加尔发电厂项目 | 方案 | C71: 方案 | D71: 2026-01-21 14:56:51 | E71: 2026-01-21 14:53:00 | F71: 2026-07-03 19:00:00 | H71: 163.2天 | J71: 崔阳
A72: 70 | B72: C00009506|崔阳|粮食| RUSAGRO大豆深度加工综合生产线|方案V1 | C72: 方案 | D72: =VLOOKUP(B72,[1]Sheet1!$A:$D,4,FALSE) -> 2026-08-13 11:02:00 | J72: 崔阳
A73: 71 | B73: C00006570|崔阳|工业|Powerz输送机采购|方案V1 | C73: 方案 | D73: =VLOOKUP(B73,[1]Sheet1!$A:$D,4,FALSE) -> 2026-07-30 17:50:53 | J73: 崔阳
A74: 72 | B74: C00009678｜冯乐｜坦桑尼亚｜小麦2×4500T装配仓项目｜方案V1 | 重点项目 | C74: 方案 | D74: 2026-07-21 09:36:12 | E74: 2026-07-21 09:20:00 | F74: 2026-07-24 20:30:00 | G74: 2026-07-23 11:45:25 | H74: 3.5天 | I74: 2.2天 | J74: 冯乐 | K74: 客户主营粮食加工，此前已接受我方报价。回国与工程团队商讨后，客户提出了新要求，我方已做技术反馈。目前客户需视其农场情况再作回复。 | L74: 进行中
A75: 73 | B75: C00009584|冯乐|粮食|尼日利亚-2×1200T玉米仓项目|方案V1 | C75: 方案 | D75: 2026-07-06 10:51:39 | E75: 2026-07-06 10:45:00 | F75: 2026-07-15 20:00:00 | G75: 2026-07-15 18:39:03 | H75: 9.4天 | I75: 9.4天 | J75: 冯乐 | K75: 目前是一位中间贸易商替业主询价，我方已提供方案和报价，多家供应商对比。 | L75: 进行中
A76: 74 | B76: C00009383｜冯乐｜工业｜也门-3×1200m³水泥装配仓项目｜方案V3 | C76: 方案 | D76: 2026-06-09 09:54:45 | E76: 2026-07-18 14:00:00 | F76: 2026-07-22 20:30:00 | G76: 2026-07-22 17:08:19 | H76: 4.3天 | I76: 4.2天 | J76: 冯乐 | K76: 已进行多次报价，客户对价格比较敏感，目前正在和对方团队进行技术澄清。 | L76: 进行中
A77: 75 | B77: C00009344｜冯乐｜工业｜土库曼斯坦火车装载料斗项目｜方案V1 | C77: 方案 | D77: 2026-05-29 10:11:40 | E77: 2026-05-29 11:00:00 | F77: 2026-06-05 19:00:00 | G77: 2026-06-06 09:30:49 | H77: 7.3天 | I77: 7.10天 | J77: 冯乐 | K77: 客户是总承包商，我们是分包，已进行过两次商务报价。整个项目比较大，我们只负责料斗报价，目前等总包更新项目进展。 | L77: 进行中
A78: 76 | B78: C00009727｜冯乐｜粮食｜阿根廷2×3000T+6×800T 储存仓项目｜方案V2 | C78: 方案 | D78: =VLOOKUP(B78,[1]Sheet1!$A:$D,4,FALSE) -> 2026-07-30 15:08:35 | J78: =VLOOKUP(B78,[1]Sheet1!$A:$J,10,FALSE) -> 冯乐 | K78: 直接业主，是一家从农田到深加工全产业链的农业综合集团，该项目是业主的规划项目。目前处于收集多方供应商的方案和报价，我方已提供商务报价。等待业主回复。 | L78: 进行中
A79: 77 | B79: C00009344｜冯乐｜新疆｜PP掺混料仓×10+PE掺混料仓×10项目｜方案V1 | C79: 方案 | D79: =VLOOKUP(B79,[1]Sheet1!$A:$D,4,FALSE) -> 2026-07-24 17:13:36 | J79: =VLOOKUP(B79,[1]Sheet1!$A:$J,10,FALSE) -> 冯乐 | K79: 客户是总承包商，我们是分包，已提供商务方案报价。 | L79: 进行中
A80: 78 | B80: 20260723|郭朝伟|新疆宏兴|镁渣筒仓|方案 | C80: 方案 | D80: 2026-07-23 08:59:23 | E80: 2026-07-23 08:57:00 | F80: 2026-07-28 17:00:00 | H80: 5.4天 | J80: 郭朝伟 | K80: 初步方案沟通中，还未确认方案 | L80: 进行中
A81: 79 | B81: 20260715|郭朝伟|河南工大|模拟粮仓|方案V1 | 重点项目 | C81: 方案 | D81: 2026-07-15 17:40:29 | E81: 2026-07-16 08:00:00 | F81: 2026-07-22 17:00:00 | G81: 2026-07-22 17:11:43 | H81: 6.4天 | I81: 6.4天 | J81: 郭朝伟 | K81: 方案基本确定，带客户确认后在沟通下一步 | L81: 进行中
A82: 80 | B82: 20260715郭朝伟 | 旺康集团 | 4*20000吨水泥仓 | 方案V1 | C82: 方案 | D82: 2026-07-15 11:06:03 | E82: 2026-07-15 11:03:00 | F82: 2026-07-20 17:00:00 | G82: 2026-07-20 16:09:29 | H82: 5.3天 | I82: 5.3天 | J82: 郭朝伟 | K82: 已确认供应商 | L82: 已结项-丢单 | M82: 一次报价之后，价差太大，客户不再愿意继续沟通，直接定供应商
A83: 81 | B83: 20260715郭朝伟 | 厦门树峰 | 4*5000T玉米仓 | 方案V1 | C83: 方案 | D83: 2026-07-15 08:40:17 | E83: 2026-07-15 08:36:00 | F83: 2026-07-20 17:00:00 | G83: 2026-07-21 15:14:24 | H83: 5.4天 | I83: 6.3天 | J83: 郭朝伟 | K83: 出方案，邀请考察中（大概率合作不成，客户明确要合作制造厂家） | L83: 进行中
A84: 82 | B84: C00009357|韩鸿彪|工业|越南水泥码头+木屑颗粒仓项目|方案V1 | C84: 方案 | D84: 2026-06-16 17:59:22 | E84: 2026-06-17 08:35:00 | F84: 2026-06-27 18:00:00 | G84: 2026-06-26 16:53:57 | H84: 10.4天 | I84: 9.4天 | J84: 韩鸿彪 | K84: 项目土地审批和银行贷款阶段，预计10月底会有进一步更新 | L84: 进行中
A85: 83 | B85: C00008493|韩鸿彪|工业|也门2x1600T水泥仓扩建项目方案V2 | C85: 方案 | D85: 2026-06-12 09:25:53 | E85: 2026-07-10 10:30:00 | F85: 2026-07-15 17:30:00 | G85: 2026-07-17 13:20:26 | H85: 5.3天 | I85: 7.2天 | J85: 韩鸿彪 | K85: 更新方案更新报价V3，业主在对比方案和报价，项目计划是27年Q1上 | L85: 进行中
A86: 84 | B86: C00008036/韩鸿彪/越南QNC料场项目/方案V2 | C86: 方案 | D86: 2026-03-03 10:14:41 | E86: 2026-05-07 11:30:00 | F86: 2026-05-14 18:30:00 | G86: 2026-05-29 16:01:31 | H86: 7.3天 | I86: 22.2天 | J86: 韩鸿彪 | K86: 项目排期后延，处于规划阶段，预计明年二季度会进行内部评估 | L86: 暂停
A87: 85 | B87: C00008843|韩鸿彪|印度Shree Cement 5000T/10000T/15000T/20000T水泥仓项目|方案 V3 | C87: 方案 | D87: 2026-02-05 14:13:18 | E87: 2026-05-22 16:30:00 | F87: 2026-05-28 16:30:00 | G87: 2026-06-01 20:08:00 | H87: 6天 | I87: 10.2天 | J87: 韩鸿彪 | K87: 等待具体项目信息，互动减弱，业主内部高层可能更偏向于混凝土仓仓型 | L87: 暂停
A88: 86 | B88: C00008036|韩鸿彪|工业|越南QNC-Halong2x1500T水泥仓方案V2 | C88: 方案 | D88: 2026-02-04 11:59:21 | E88: 2026-06-04 10:30:00 | F88: 2026-06-10 16:41:00 | G88: 2026-06-10 16:39:10 | H88: 6.3天 | I88: 6.3天 | J88: 韩鸿彪 | K88: 越南4x6000业主的客户，等待业主的跟进反馈，配合性项目不做重点 | L88: 进行中
A89: 87 | B89: 韩鸿彪 20260128 巴拿马28x2500T粮库改造项目方案 | C89: 方案 | D89: 2026-01-28 09:48:11 | E89: 2026-01-28 09:43:00 | F89: 2026-02-12 19:00:00 | G89: 2026-02-12 16:08:12 | H89: 15.4天 | I89: 15.3天 | J89: 韩鸿彪 | K89: 联系人为中间工程公司，对项目把控性弱，项目信息不全，目前已失去联系 | L89: 已结项-丢单 | M89: 非终端业主，项目信息不全，意向不明确
A90: 88 | B90: 20260120 韩鸿彪 越南广宁水泥4*6000T筒仓配套装船钢结构雨棚（河边雨棚） | C90: 方案 | D90: 2026-01-20 14:33:03 | E90: 2026-01-20 14:25:00 | F90: 2026-01-23 18:00:00 | G90: 2026-01-23 17:24:52 | H90: 3.2天 | I90: 3.2天 | J90: 韩鸿彪 | K90: 土地报批手续中，杰余报建水槽手续复杂和预算原因，可能会放弃该项目建设 | L90: 进行中
A91: 89 | B91: C00008036 韩鸿彪 越南 4x6000T筒仓系统配套输送设备方案 V5 | C91: 方案 | D91: 2026-01-19 17:18:40 | E91: 2026-04-29 15:00:00 | F91: 2026-04-30 18:00:00 | G91: 2026-04-30 15:53:06 | H91: 1.1天 | I91: 1.1天 | J91: 韩鸿彪 | K91: 更新方案，更新报价，等待决策。业主计划先上一条（6台）包装线，第一个筒仓完工后先运行起来 | L91: 进行中
A92: 90 | B92: 20260108 韩鸿彪 越南广宁水泥4*5000T筒仓配套装船钢结构雨棚 | C92: 方案 | D92: 2026-01-08 15:12:03 | E92: 2026-01-14 15:00:00 | F92: 2026-01-15 14:00:00 | G92: 2026-01-15 13:12:18 | H92: 1天 | I92: 0.10天 | J92: 韩鸿彪 | K92: 与86重复
A93: 91 | B93: C00009474|韩鸿彪|粮食|卢旺达面粉厂3x2500T小麦仓项目|方案V1 | C93: 方案 | D93: =VLOOKUP(B93,[1]Sheet1!$A:$D,4,FALSE) -> 2026-07-31 17:00:38 | J93: =VLOOKUP(B93,[1]Sheet1!$A:$J,10,FALSE) -> 韩鸿彪 | K93: 面粉厂扩建项目，规模不大，但项目真实，第一版报价阶段 | L93: 进行中
A94: 92 | B94: C00008036|韩鸿彪|工业|越南QNC船对船水泥输送系统|方案V1 | C94: 方案 | D94: =VLOOKUP(B94,[1]Sheet1!$A:$D,4,FALSE) -> 2026-07-30 16:22:22 | J94: =VLOOKUP(B94,[1]Sheet1!$A:$J,10,FALSE) -> 韩鸿彪 | K94: 第一版报价后，我司报价过高，业主需要的方案我们不能满足，暂停更新 | L94: 暂停
A95: 93 | B95: C00009797 | 马鹏飞 | 工业 | 新加坡波纹钢板储水罐 | 方案V1 | | C95: 方案 | D95: 2026-07-22 10:56:25 | E95: 2026-07-22 10:31:00 | F95: 2026-07-24 18:00:00 | G95: 2026-07-24 17:10:56 | H95: 2.3天 | I95: 2.3天 | J95: 马鹏飞 | K95: 业主仍在投标，目前项目延标，预计2026年底投标 | L95: 进行中
A96: 94 | B96: C00009713 | 马鹏飞 | 工业 | 保加利亚DPM Metals Inc. 50吨消石灰仓及设备 | 方案V1 | | C96: 方案 | D96: 2026-07-07 18:28:51 | E96: 2026-07-08 08:00:00 | F96: 2026-07-10 12:00:00 | G96: 2026-07-10 11:21:57 | H96: 2.2天 | I96: 2.2天 | J96: 马鹏飞 | K96: 50吨小仓，客户对我公司项目澄清未回，客户兴趣不大，不再报价 | L96: 已结项-丢单 | M96: 客户失联
A97: 95 | B97: C00009340 | 马鹏飞 | 粮食 | 澳大利亚维多利亚州 农场主 3 +1 个1000吨大麦小麦存储仓 | 方案V1 | | C97: 方案 | D97: 2026-05-26 14:53:11 | E97: 2026-05-26 14:12:00 | F97: 2026-06-04 17:00:00 | G97: 2026-06-04 14:08:30 | H97: 9.1天 | I97: 8.10天 | J97: 马鹏飞 | K97: 客户比价倾向重，澳洲标准，项目需要落实澄清客户未回，主动联系不再回复，故不再报价 | L97: 已结项-丢单 | M97: 客户失联
A98: 96 | B98: C00006463 | 马鹏飞 | 粮食 | 智利 Empresasalacarta公司麦麸料斗 | 方案V1 | | C98: 方案 | D98: 2026-05-19 14:18:07 | E98: 2026-05-19 14:14:00 | F98: 2026-06-03 19:00:00 | H98: 15.2天 | J98: 马鹏飞 | K98: 项目图纸有尺寸错误，向业主澄清未回，主动联系不再回复，故不再报价 | L98: 已结项-丢单 | M98: 客户失联
A99: 97 | B99: C00009133 | 马鹏飞 | 粮食 | 科特迪瓦代理可可豆长期存储项目| 方案V2 | | C99: 方案 | D99: 2026-04-14 16:41:09 | E99: 2026-04-14 16:36:00 | F99: 2026-06-06 19:00:00 | G99: 2026-06-05 11:00:03 | H99: 53.1天 | I99: 51.8天 | J99: 马鹏飞 | K99: 已做方案，目前改与中国电建合作，准备相关研究报告 | L99: 已结项-丢单 | M99: 风险巨大
A100: 98 | B100: C00008933 | 马鹏飞 | 工业 | Técnicas Reunidas S. A.（意大利头部国际 EPC/工程总承包集团）小型石灰仓 | 方案V1 | | C100: 方案 | D100: 2026-03-17 11:28:24 | E100: 2026-03-17 11:20:00 | F100: 2026-03-28 19:00:00 | G100: 2026-03-28 16:02:28 | H100: 11.3天 | I100: 11.2天 | J100: 马鹏飞 | K100: 已做方案，及报价15吨小仓，项目污泥刮板机无法做，客户联络不回 | L100: 已结项-丢单 | M100: 项目污泥刮板机无法做
...
